{
  "period": "2026-06",
  "period_label": "2026년 6월",
  "brand": "슬룸",
  "generated_at": "2026-04-22",
  "note": "V10: CX 매니저 태그 + ALF 폴백 매칭 (manager > ALF요약 > 첫메시지 > user전체) — V12 SKU + 목베개 폴백 (2026-05-04)",
  "summary": {
    "total_shipments": 1284,
    "total_inquiries": 5367,
    "chat_inquiries": 5360,
    "call_ob_inquiries": 7,
    "ipv": 417.99,
    "ipv_chat": 417.45,
    "ipv_call": 0.55,
    "board_inquiries": 0,
    "_inquiry_note": "채널톡 5,367건 + 게시판/메일 0건 (게시판/메일은 유형 분류 미적용)",
    "ipv_board": 0.0,
    "_ipv_note": "IPV 합산 = 채널톡(417.45%) + OB콜(0.55%) + 게시판/메일(0.0%) = 417.99%",
    "total_chats": 5367
  },
  "by_product": [
    {
      "name": "허리베개 프로",
      "shipments": 501,
      "inquiries": 23,
      "ipv": 4.59
    },
    {
      "name": "목편한케어",
      "shipments": 139,
      "inquiries": 24,
      "ipv": 17.27
    },
    {
      "name": "발편한케어 V1",
      "shipments": 87,
      "inquiries": 105,
      "ipv": 120.69
    },
    {
      "name": "목베개 플러스",
      "shipments": 68,
      "inquiries": 469,
      "ipv": 689.71
    },
    {
      "name": "허리편한케어 V1",
      "shipments": 60,
      "inquiries": 66,
      "ipv": 110.0
    },
    {
      "name": "넥숄더 프로",
      "shipments": 50,
      "inquiries": 41,
      "ipv": 82.0
    },
    {
      "name": "목 마사지 베개 V2",
      "shipments": 48,
      "inquiries": 432,
      "ipv": 900.0
    },
    {
      "name": "눈편한케어",
      "shipments": 46,
      "inquiries": 6,
      "ipv": 13.04
    },
    {
      "name": "허리편한케어 V2",
      "shipments": 27,
      "inquiries": 189,
      "ipv": 700.0
    },
    {
      "name": "목편한케어 플라잉",
      "shipments": 26,
      "inquiries": 55,
      "ipv": 211.54
    },
    {
      "name": "넥숄더 힐링케어",
      "shipments": 18,
      "inquiries": 10,
      "ipv": 55.56
    },
    {
      "name": "허리베개",
      "shipments": 10,
      "inquiries": 3,
      "ipv": 30.0
    },
    {
      "name": "넥숄더 힐링케어 V2",
      "shipments": 7,
      "inquiries": 17,
      "ipv": 242.86
    },
    {
      "name": "종아리 편한케어",
      "shipments": 6,
      "inquiries": 0,
      "ipv": 0.0
    },
    {
      "name": "허리편한케어 마스터",
      "shipments": 5,
      "inquiries": 11,
      "ipv": 220.0
    },
    {
      "name": "발편한케어 V2",
      "shipments": 3,
      "inquiries": 54,
      "ipv": 1800.0
    }
  ],
  "by_inquiry_type": [],
  "by_inquiry_type_cx": [
    {
      "type": "제품/사용문의",
      "count": 667,
      "ratio": 27.1
    },
    {
      "type": "유상 AS",
      "count": 373,
      "ratio": 15.2
    },
    {
      "type": "불량 확정",
      "count": 356,
      "ratio": 14.5
    },
    {
      "type": "반품/환불",
      "count": 352,
      "ratio": 14.3
    },
    {
      "type": "기타",
      "count": 306,
      "ratio": 12.4
    },
    {
      "type": "100% 환불 이벤트",
      "count": 185,
      "ratio": 7.5
    },
    {
      "type": "배송문의",
      "count": 93,
      "ratio": 3.8
    },
    {
      "type": "교환",
      "count": 56,
      "ratio": 2.3
    },
    {
      "type": "주문/결제",
      "count": 43,
      "ratio": 1.7
    },
    {
      "type": "이벤트/쿠폰",
      "count": 16,
      "ratio": 0.7
    },
    {
      "type": "불량 미확정",
      "count": 11,
      "ratio": 0.4
    },
    {
      "type": "리뷰",
      "count": 2,
      "ratio": 0.1
    }
  ],
  "by_inquiry_type_alf": [],
  "by_channel": [
    {
      "channel": "카카오 선물하기",
      "shipments": 986,
      "inquiries": 0,
      "ipv": 0
    },
    {
      "channel": "자사몰",
      "shipments": 155,
      "inquiries": 0,
      "ipv": 0
    },
    {
      "channel": "새날마켓",
      "shipments": 18,
      "inquiries": 0,
      "ipv": 0
    },
    {
      "channel": "신라면세점",
      "shipments": 25,
      "inquiries": 0,
      "ipv": 0
    },
    {
      "channel": "주니버스",
      "shipments": 100,
      "inquiries": 0,
      "ipv": 0
    }
  ],
  "by_product_detail": [
    {
      "name": "넥숄더 프로",
      "shipments": 50,
      "desc_matched": 41,
      "by_type": [
        {
          "type": "제품/사용문의",
          "count": 17,
          "ratio": 41.5
        },
        {
          "type": "불량 확정",
          "count": 10,
          "ratio": 24.4
        },
        {
          "type": "유상 AS",
          "count": 6,
          "ratio": 14.6
        },
        {
          "type": "반품/환불",
          "count": 4,
          "ratio": 9.8
        },
        {
          "type": "기타",
          "count": 3,
          "ratio": 7.3
        },
        {
          "type": "100% 환불 이벤트",
          "count": 1,
          "ratio": 2.4
        }
      ],
      "defect_detail": [],
      "defect_total": 16,
      "return_detail": [],
      "return_total": 0
    },
    {
      "name": "넥숄더 힐링케어",
      "shipments": 18,
      "desc_matched": 10,
      "by_type": [
        {
          "type": "유상 AS",
          "count": 4,
          "ratio": 40.0
        },
        {
          "type": "제품/사용문의",
          "count": 3,
          "ratio": 30.0
        },
        {
          "type": "기타",
          "count": 2,
          "ratio": 20.0
        },
        {
          "type": "불량 미확정",
          "count": 1,
          "ratio": 10.0
        }
      ],
      "defect_detail": [],
      "defect_total": 5,
      "return_detail": [],
      "return_total": 0
    },
    {
      "name": "넥숄더 힐링케어 V2",
      "shipments": 7,
      "desc_matched": 17,
      "by_type": [
        {
          "type": "제품/사용문의",
          "count": 7,
          "ratio": 41.2
        },
        {
          "type": "유상 AS",
          "count": 5,
          "ratio": 29.4
        },
        {
          "type": "불량 확정",
          "count": 3,
          "ratio": 17.6
        },
        {
          "type": "이벤트/쿠폰",
          "count": 1,
          "ratio": 5.9
        },
        {
          "type": "교환",
          "count": 1,
          "ratio": 5.9
        }
      ],
      "defect_detail": [],
      "defect_total": 8,
      "return_detail": [],
      "return_total": 0
    },
    {
      "name": "눈편한케어",
      "shipments": 46,
      "desc_matched": 6,
      "by_type": [
        {
          "type": "100% 환불 이벤트",
          "count": 3,
          "ratio": 50.0
        },
        {
          "type": "유상 AS",
          "count": 2,
          "ratio": 33.3
        },
        {
          "type": "불량 확정",
          "count": 1,
          "ratio": 16.7
        }
      ],
      "defect_detail": [],
      "defect_total": 3,
      "return_detail": [],
      "return_total": 0
    },
    {
      "name": "목 마사지 베개 V2",
      "shipments": 48,
      "desc_matched": 432,
      "by_type": [
        {
          "type": "불량 확정",
          "count": 152,
          "ratio": 35.2
        },
        {
          "type": "제품/사용문의",
          "count": 83,
          "ratio": 19.2
        },
        {
          "type": "100% 환불 이벤트",
          "count": 63,
          "ratio": 14.6
        },
        {
          "type": "유상 AS",
          "count": 52,
          "ratio": 12.0
        },
        {
          "type": "반품/환불",
          "count": 39,
          "ratio": 9.0
        },
        {
          "type": "배송문의",
          "count": 11,
          "ratio": 2.5
        },
        {
          "type": "기타",
          "count": 10,
          "ratio": 2.3
        },
        {
          "type": "불량 미확정",
          "count": 10,
          "ratio": 2.3
        },
        {
          "type": "이벤트/쿠폰",
          "count": 4,
          "ratio": 0.9
        },
        {
          "type": "주문/결제",
          "count": 4,
          "ratio": 0.9
        },
        {
          "type": "교환",
          "count": 2,
          "ratio": 0.5
        },
        {
          "type": "리뷰",
          "count": 2,
          "ratio": 0.5
        }
      ],
      "defect_detail": [],
      "defect_total": 214,
      "return_detail": [],
      "return_total": 0
    },
    {
      "name": "목베개 플러스",
      "shipments": 68,
      "desc_matched": 469,
      "by_type": [
        {
          "type": "제품/사용문의",
          "count": 171,
          "ratio": 36.5
        },
        {
          "type": "불량 확정",
          "count": 76,
          "ratio": 16.2
        },
        {
          "type": "100% 환불 이벤트",
          "count": 64,
          "ratio": 13.6
        },
        {
          "type": "유상 AS",
          "count": 49,
          "ratio": 10.4
        },
        {
          "type": "반품/환불",
          "count": 35,
          "ratio": 7.5
        },
        {
          "type": "기타",
          "count": 33,
          "ratio": 7.0
        },
        {
          "type": "불량 미확정",
          "count": 14,
          "ratio": 3.0
        },
        {
          "type": "이벤트/쿠폰",
          "count": 13,
          "ratio": 2.8
        },
        {
          "type": "주문/결제",
          "count": 9,
          "ratio": 1.9
        },
        {
          "type": "교환",
          "count": 3,
          "ratio": 0.6
        },
        {
          "type": "배송문의",
          "count": 2,
          "ratio": 0.4
        }
      ],
      "defect_detail": [],
      "defect_total": 139,
      "return_detail": [],
      "return_total": 0
    },
    {
      "name": "목편한케어",
      "shipments": 139,
      "desc_matched": 24,
      "by_type": [
        {
          "type": "제품/사용문의",
          "count": 12,
          "ratio": 50.0
        },
        {
          "type": "불량 확정",
          "count": 5,
          "ratio": 20.8
        },
        {
          "type": "기타",
          "count": 3,
          "ratio": 12.5
        },
        {
          "type": "유상 AS",
          "count": 2,
          "ratio": 8.3
        },
        {
          "type": "불량 미확정",
          "count": 1,
          "ratio": 4.2
        },
        {
          "type": "반품/환불",
          "count": 1,
          "ratio": 4.2
        }
      ],
      "defect_detail": [],
      "defect_total": 8,
      "return_detail": [],
      "return_total": 0
    },
    {
      "name": "목편한케어 플라잉",
      "shipments": 26,
      "desc_matched": 55,
      "by_type": [
        {
          "type": "제품/사용문의",
          "count": 19,
          "ratio": 34.5
        },
        {
          "type": "유상 AS",
          "count": 18,
          "ratio": 32.7
        },
        {
          "type": "불량 확정",
          "count": 6,
          "ratio": 10.9
        },
        {
          "type": "기타",
          "count": 4,
          "ratio": 7.3
        },
        {
          "type": "불량 미확정",
          "count": 3,
          "ratio": 5.5
        },
        {
          "type": "100% 환불 이벤트",
          "count": 2,
          "ratio": 3.6
        },
        {
          "type": "주문/결제",
          "count": 2,
          "ratio": 3.6
        },
        {
          "type": "교환",
          "count": 1,
          "ratio": 1.8
        }
      ],
      "defect_detail": [],
      "defect_total": 27,
      "return_detail": [],
      "return_total": 0
    },
    {
      "name": "발편한케어 V1",
      "shipments": 87,
      "desc_matched": 105,
      "by_type": [
        {
          "type": "제품/사용문의",
          "count": 35,
          "ratio": 33.3
        },
        {
          "type": "기타",
          "count": 17,
          "ratio": 16.2
        },
        {
          "type": "유상 AS",
          "count": 13,
          "ratio": 12.4
        },
        {
          "type": "불량 확정",
          "count": 11,
          "ratio": 10.5
        },
        {
          "type": "100% 환불 이벤트",
          "count": 9,
          "ratio": 8.6
        },
        {
          "type": "불량 미확정",
          "count": 6,
          "ratio": 5.7
        },
        {
          "type": "반품/환불",
          "count": 6,
          "ratio": 5.7
        },
        {
          "type": "배송문의",
          "count": 3,
          "ratio": 2.9
        },
        {
          "type": "이벤트/쿠폰",
          "count": 3,
          "ratio": 2.9
        },
        {
          "type": "주문/결제",
          "count": 2,
          "ratio": 1.9
        }
      ],
      "defect_detail": [],
      "defect_total": 30,
      "return_detail": [],
      "return_total": 0
    },
    {
      "name": "발편한케어 V2",
      "shipments": 3,
      "desc_matched": 54,
      "by_type": [
        {
          "type": "반품/환불",
          "count": 12,
          "ratio": 22.2
        },
        {
          "type": "제품/사용문의",
          "count": 9,
          "ratio": 16.7
        },
        {
          "type": "100% 환불 이벤트",
          "count": 8,
          "ratio": 14.8
        },
        {
          "type": "불량 확정",
          "count": 8,
          "ratio": 14.8
        },
        {
          "type": "유상 AS",
          "count": 6,
          "ratio": 11.1
        },
        {
          "type": "기타",
          "count": 4,
          "ratio": 7.4
        },
        {
          "type": "교환",
          "count": 2,
          "ratio": 3.7
        },
        {
          "type": "주문/결제",
          "count": 2,
          "ratio": 3.7
        },
        {
          "type": "이벤트/쿠폰",
          "count": 1,
          "ratio": 1.9
        },
        {
          "type": "배송문의",
          "count": 1,
          "ratio": 1.9
        },
        {
          "type": "리뷰",
          "count": 1,
          "ratio": 1.9
        }
      ],
      "defect_detail": [],
      "defect_total": 14,
      "return_detail": [],
      "return_total": 0
    },
    {
      "name": "종아리 편한케어",
      "shipments": 6,
      "desc_matched": 0,
      "by_type": [],
      "defect_detail": [],
      "defect_total": 0,
      "return_detail": [],
      "return_total": 0
    },
    {
      "name": "허리베개",
      "shipments": 10,
      "desc_matched": 3,
      "by_type": [
        {
          "type": "교환",
          "count": 2,
          "ratio": 66.7
        },
        {
          "type": "반품/환불",
          "count": 1,
          "ratio": 33.3
        }
      ],
      "defect_detail": [],
      "defect_total": 0,
      "return_detail": [],
      "return_total": 0
    },
    {
      "name": "허리베개 프로",
      "shipments": 501,
      "desc_matched": 23,
      "by_type": [
        {
          "type": "제품/사용문의",
          "count": 8,
          "ratio": 34.8
        },
        {
          "type": "불량 확정",
          "count": 8,
          "ratio": 34.8
        },
        {
          "type": "유상 AS",
          "count": 4,
          "ratio": 17.4
        },
        {
          "type": "기타",
          "count": 1,
          "ratio": 4.3
        },
        {
          "type": "배송문의",
          "count": 1,
          "ratio": 4.3
        },
        {
          "type": "반품/환불",
          "count": 1,
          "ratio": 4.3
        }
      ],
      "defect_detail": [],
      "defect_total": 12,
      "return_detail": [],
      "return_total": 0
    },
    {
      "name": "허리편한케어 V1",
      "shipments": 60,
      "desc_matched": 66,
      "by_type": [
        {
          "type": "제품/사용문의",
          "count": 32,
          "ratio": 48.5
        },
        {
          "type": "유상 AS",
          "count": 14,
          "ratio": 21.2
        },
        {
          "type": "불량 미확정",
          "count": 7,
          "ratio": 10.6
        },
        {
          "type": "기타",
          "count": 5,
          "ratio": 7.6
        },
        {
          "type": "주문/결제",
          "count": 4,
          "ratio": 6.1
        },
        {
          "type": "100% 환불 이벤트",
          "count": 2,
          "ratio": 3.0
        },
        {
          "type": "이벤트/쿠폰",
          "count": 1,
          "ratio": 1.5
        },
        {
          "type": "배송문의",
          "count": 1,
          "ratio": 1.5
        }
      ],
      "defect_detail": [],
      "defect_total": 21,
      "return_detail": [],
      "return_total": 0
    },
    {
      "name": "허리편한케어 V2",
      "shipments": 27,
      "desc_matched": 189,
      "by_type": [
        {
          "type": "유상 AS",
          "count": 58,
          "ratio": 30.7
        },
        {
          "type": "제품/사용문의",
          "count": 47,
          "ratio": 24.9
        },
        {
          "type": "불량 확정",
          "count": 27,
          "ratio": 14.3
        },
        {
          "type": "100% 환불 이벤트",
          "count": 20,
          "ratio": 10.6
        },
        {
          "type": "반품/환불",
          "count": 13,
          "ratio": 6.9
        },
        {
          "type": "기타",
          "count": 7,
          "ratio": 3.7
        },
        {
          "type": "배송문의",
          "count": 6,
          "ratio": 3.2
        },
        {
          "type": "교환",
          "count": 4,
          "ratio": 2.1
        },
        {
          "type": "이벤트/쿠폰",
          "count": 3,
          "ratio": 1.6
        },
        {
          "type": "불량 미확정",
          "count": 2,
          "ratio": 1.1
        },
        {
          "type": "주문/결제",
          "count": 2,
          "ratio": 1.1
        }
      ],
      "defect_detail": [],
      "defect_total": 87,
      "return_detail": [],
      "return_total": 0
    },
    {
      "name": "허리편한케어 마스터",
      "shipments": 5,
      "desc_matched": 11,
      "by_type": [
        {
          "type": "유상 AS",
          "count": 5,
          "ratio": 45.5
        },
        {
          "type": "불량 확정",
          "count": 2,
          "ratio": 18.2
        },
        {
          "type": "제품/사용문의",
          "count": 2,
          "ratio": 18.2
        },
        {
          "type": "불량 미확정",
          "count": 1,
          "ratio": 9.1
        },
        {
          "type": "반품/환불",
          "count": 1,
          "ratio": 9.1
        }
      ],
      "defect_detail": [],
      "defect_total": 8,
      "return_detail": [],
      "return_total": 0
    }
  ],
  "by_defect_return": {
    "total_return": 808,
    "total_defect": 741,
    "return_reasons": [
      {
        "reason": "단순 변심",
        "count": 116,
        "ratio": 14.4
      },
      {
        "reason": "불량",
        "count": 33,
        "ratio": 4.1
      },
      {
        "reason": "100% 환불 이벤트",
        "count": 44,
        "ratio": 5.4
      },
      {
        "reason": "사유 분류 불가",
        "count": 615,
        "ratio": 76.1
      }
    ],
    "defect_types": [
      {
        "type": "불량 확정",
        "count": 356,
        "ratio": 48.0
      },
      {
        "type": "불량 미확정",
        "count": 11,
        "ratio": 1.5
      },
      {
        "type": "유상 AS",
        "count": 374,
        "ratio": 50.5
      }
    ],
    "by_product": [],
    "_recalc_note": "V7b: 4가지 케이스 + SKU 폴백 (manager > ALF요약 > 첫메시지)",
    "confirmed_breakdown": [
      {
        "type": "교환",
        "count": 247,
        "ratio": 69.4
      },
      {
        "type": "반품·환불",
        "count": 107,
        "ratio": 30.1
      },
      {
        "type": "미처리/확인 중",
        "count": 2,
        "ratio": 0.6
      }
    ]
  },
  "by_inquiry_type_total": [
    {
      "type": "기타",
      "count": 1663,
      "ratio": 31.0
    },
    {
      "type": "제품/사용문의",
      "count": 842,
      "ratio": 15.7
    },
    {
      "type": "반품/환불",
      "count": 812,
      "ratio": 15.1
    },
    {
      "type": "100% 환불 이벤트",
      "count": 761,
      "ratio": 14.2
    },
    {
      "type": "유상 AS",
      "count": 379,
      "ratio": 7.1
    },
    {
      "type": "불량 확정",
      "count": 356,
      "ratio": 6.6
    },
    {
      "type": "불량 미확정",
      "count": 148,
      "ratio": 2.8
    },
    {
      "type": "배송문의",
      "count": 138,
      "ratio": 2.6
    },
    {
      "type": "주문/결제",
      "count": 98,
      "ratio": 1.8
    },
    {
      "type": "교환",
      "count": 88,
      "ratio": 1.6
    },
    {
      "type": "이벤트/쿠폰",
      "count": 79,
      "ratio": 1.5
    },
    {
      "type": "리뷰",
      "count": 3,
      "ratio": 0.1
    }
  ],
  "by_inquiry_type_unclassified": []
}